Metadata-Version: 2.1
Name: odoo12-addon-rma
Version: 12.0.2.6.0
Summary: Return Merchandise Authorization (RMA)
Home-page: https://github.com/OCA/rma
Author: Tecnativa, Odoo Community Association (OCA)
Author-email: support@odoo-community.org
License: AGPL-3
Platform: UNKNOWN
Classifier: Programming Language :: Python
Classifier: Framework :: Odoo
Classifier: License :: OSI Approved :: GNU Affero General Public License v3
Classifier: Development Status :: 5 - Production/Stable
Requires-Python: >=3.5
Requires-Dist: odoo (<12.1dev,>=12.0a)
